Metadata-Version: 2.1
Name: pytract
Version: 0.0.4
Summary: Smart contract Python API generator.
Home-page: https://github.com/james4ever0/pytract
Provides-Extra: simular
Provides-Extra: all
License-File: LICENSE
